[
  {
    "slug": "bland-associates-cpa-pc-omaha",
    "name": "Bland & Associates, CPA, PC",
    "city": "Omaha",
    "state": "NE",
    "address": "450 Regency Pkwy # 340, Omaha, NE 68114-3777",
    "lat": 41.2565,
    "lng": -95.9345,
    "phone": "Not provided",
    "website": "https://blandcpa.com/services/forensic-accounting-services/",
    "email": "info@BlandCPA.com",
    "contact_form_url": "",
    "contact_method": "",
    "rating": 0,
    "review_count": 0,
    "description": "Forensic accounting, valuation, and litigation support services for law firms, businesses, creditor groups, insurance companies, and individuals",
    "certifications": [],
    "services": [
      "Forensic accounting",
      "Valuation",
      "Litigation support"
    ],
    "years_experience": null,
    "coverage_area": "",
    "equipment": [],
    "claimed": false,
    "featured": false,
    "source": "perplexity",
    "scraped_at": "2026-04-26 15:06:56",
    "sentiment": null
  },
  {
    "slug": "brubaker-cpa-llc-omaha",
    "name": "Brubaker CPA, LLC",
    "city": "Omaha",
    "state": "NE",
    "address": "Not provided",
    "lat": 41.2565,
    "lng": -95.9345,
    "phone": "Not provided",
    "website": "https://www.brubakercpa.com/what-we-do",
    "email": "605a7baede844d278b89dc95ae0a9123@sentry-next.wixpress.com",
    "contact_form_url": "",
    "contact_method": "",
    "rating": 0,
    "review_count": 0,
    "description": "Corporate, individual, agricultural and self-employed tax and accounting services including fraud examination and forensic accounting. Partners with law enforcement and District Attorneys on high-dollar fraud cases",
    "certifications": [],
    "services": [
      "Corporate tax services",
      "Individual tax services",
      "Agricultural tax services",
      "Payroll",
      "Fraud examination",
      "Forensic accounting",
      "Litigation support"
    ],
    "years_experience": null,
    "coverage_area": "",
    "equipment": [],
    "claimed": false,
    "featured": false,
    "source": "perplexity",
    "scraped_at": "2026-04-26 15:06:56",
    "sentiment": null
  },
  {
    "slug": "clawson-associates-pc-omaha",
    "name": "Clawson Associates, P.C.",
    "city": "Omaha",
    "state": "NE",
    "address": "8424 W Center Rd # 205, Omaha, NE 68124-3138",
    "lat": 41.2565,
    "lng": -95.9345,
    "phone": "Not provided",
    "website": "Not provided",
    "email": "",
    "contact_form_url": "",
    "contact_method": "",
    "rating": 0,
    "review_count": 0,
    "description": "CPA firm offering tax return preparation and financial services with forensic accounting capabilities",
    "certifications": [],
    "services": [
      "CPA services",
      "Tax return preparation",
      "Financial services",
      "Forensic accounting"
    ],
    "years_experience": null,
    "coverage_area": "",
    "equipment": [],
    "claimed": false,
    "featured": false,
    "source": "perplexity",
    "scraped_at": "2026-04-26 15:06:56",
    "sentiment": null
  },
  {
    "slug": "cremerscpa-omaha",
    "name": "CremersCPA",
    "city": "Omaha",
    "state": "NE",
    "address": "3628 N 163 Plaza, Omaha, NE 68116",
    "lat": 41.2565,
    "lng": -95.9345,
    "phone": "(402) 934-2922",
    "website": "https://cremerscpa.com/litigation-support-forensic-accounting/",
    "email": "",
    "contact_form_url": "",
    "contact_method": "",
    "rating": 0,
    "review_count": 0,
    "description": "Litigation support and forensic accounting services for legal professionals, businesses, and individuals in the Omaha metro area",
    "certifications": [],
    "services": [
      "Litigation support",
      "Forensic accounting"
    ],
    "years_experience": null,
    "coverage_area": "",
    "equipment": [],
    "claimed": false,
    "featured": false,
    "source": "perplexity",
    "scraped_at": "2026-04-26 15:06:56",
    "sentiment": null
  },
  {
    "slug": "dana-f-cole-company-llp-omaha",
    "name": "Dana F. Cole & Company, L.L.P.",
    "city": "Omaha",
    "state": "NE",
    "address": "2809 S 160th St, Omaha, NE 68130-1754",
    "lat": 41.232704,
    "lng": -96.164449,
    "phone": "(402) 827-1450",
    "website": "Not provided",
    "email": "",
    "contact_form_url": "",
    "contact_method": "",
    "rating": 0,
    "review_count": 0,
    "description": "CPA firm providing tax return preparation and tax consulting services",
    "certifications": [],
    "services": [
      "CPA services",
      "Tax return preparation",
      "Tax consulting"
    ],
    "years_experience": null,
    "coverage_area": "",
    "equipment": [],
    "claimed": false,
    "featured": false,
    "source": "perplexity",
    "scraped_at": "2026-04-26 15:06:56",
    "sentiment": null
  },
  {
    "slug": "darst-brune-associates-llc-omaha",
    "name": "Darst, Brune & Associates, LLC",
    "city": "Omaha",
    "state": "NE",
    "address": "14707 California St # 10, Omaha, NE 68154-1900",
    "lat": 41.2587459,
    "lng": -95.9383758,
    "phone": "Not provided",
    "website": "Not provided",
    "email": "",
    "contact_form_url": "",
    "contact_method": "",
    "rating": 0,
    "review_count": 0,
    "description": "CPA firm providing tax return preparation and tax consulting with forensic accounting services",
    "certifications": [],
    "services": [
      "CPA services",
      "Tax return preparation",
      "Tax consulting",
      "Forensic accounting"
    ],
    "years_experience": null,
    "coverage_area": "",
    "equipment": [],
    "claimed": false,
    "featured": false,
    "source": "perplexity",
    "scraped_at": "2026-04-26 15:06:56",
    "sentiment": null
  },
  {
    "slug": "forensic-accounting-corp-omaha",
    "name": "Forensic Accounting Corp",
    "city": "Omaha",
    "state": "NE",
    "address": "Not provided",
    "lat": 41.2565,
    "lng": -95.9345,
    "phone": "(402) 445-0109",
    "website": "https://forensicaccountingcorp.com/locations/omaha",
    "email": "",
    "contact_form_url": "",
    "contact_method": "",
    "rating": 0,
    "review_count": 0,
    "description": "Full-range forensic accounting solutions including identifying financial discrepancies, calculating damages and economic damages quantification, embezzlement investigation, business valuation, insurance claims, fraud and cybercrime investigation, and litigation support",
    "certifications": [],
    "services": [
      "Calculating damages",
      "Economic damages quantification",
      "Identifying financial discrepancies",
      "Embezzlement investigation",
      "Business valuation",
      "Insurance claims",
      "Fraud investigation",
      "Cybercrime investigation",
      "Litigation support",
      "Digital evidence preservation",
      "ESI analysis"
    ],
    "years_experience": null,
    "coverage_area": "",
    "equipment": [],
    "claimed": false,
    "featured": false,
    "source": "perplexity",
    "scraped_at": "2026-04-26 15:06:56",
    "sentiment": null
  },
  {
    "slug": "hamilton-associates-pc-omaha",
    "name": "Hamilton Associates, PC",
    "city": "Omaha",
    "state": "NE",
    "address": "12335 Gold St, Omaha, NE 68144-2760",
    "lat": 41.2565,
    "lng": -95.9345,
    "phone": "(402) 333-0393",
    "website": "Not provided",
    "email": "",
    "contact_form_url": "",
    "contact_method": "",
    "rating": 0,
    "review_count": 0,
    "description": "CPA firm offering tax return preparation and tax consulting with forensic accounting capabilities",
    "certifications": [],
    "services": [
      "CPA services",
      "Tax return preparation",
      "Tax consulting",
      "Forensic accounting"
    ],
    "years_experience": null,
    "coverage_area": "",
    "equipment": [],
    "claimed": false,
    "featured": false,
    "source": "perplexity",
    "scraped_at": "2026-04-26 15:06:56",
    "sentiment": null
  },
  {
    "slug": "robert-l-kirchner-assoc-inc-omaha",
    "name": "Robert L Kirchner & Assoc., Inc.",
    "city": "Omaha",
    "state": "NE",
    "address": "Not provided",
    "lat": 41.2565,
    "lng": -95.9345,
    "phone": "Not provided",
    "website": "https://www.robertlkirnerinc.com/forensic-accounting",
    "email": "",
    "contact_form_url": "",
    "contact_method": "",
    "rating": 0,
    "review_count": 0,
    "description": "Forensic accounting specializing in complex financial litigation, pension audits, and pension plans. Services include divorce, bankruptcy, and insurance claims matters",
    "certifications": [],
    "services": [
      "Forensic accounting",
      "Complex financial litigation",
      "Pension audits",
      "Pension plans",
      "Divorce accounting",
      "Bankruptcy accounting",
      "Insurance claims"
    ],
    "years_experience": null,
    "coverage_area": "",
    "equipment": [],
    "claimed": false,
    "featured": false,
    "source": "perplexity",
    "scraped_at": "2026-04-26 15:06:56",
    "sentiment": null
  }
]